{
  "id": "9D7C150F93C6484BB3F97A97A3384DAD",
  "title": "Grade 8",
  "subject": "Social Studies (2023-)",
  "normalizedSubject": null,
  "educationLevels": [
    "08"
  ],
  "cspStatus": {
    "value": "visible",
    "notes": null
  },
  "license": {
    "title": "CC BY 4.0 US",
    "URL": "http://creativecommons.org/licenses/by/4.0/us/",
    "rightsHolder": "Common Curriculum, Inc."
  },
  "document": {
    "title": "Washington, DC K-12 Social Studies Standards Revised Standards",
    "sourceURL": "https://osse.dc.gov/sites/default/files/dc/sites/osse/page_content/attachments/Adopted%20Standards%20(July%202023).pdf",
    "publicationStatus": "Published"
  },
  "jurisdiction": {
    "id": "A5C1DF532ED44A6CB3D000FD37370C0F",
    "title": "District of Columbia"
  },
  "standards": {
    "73143A089AC84FC28AD7F430329038B6": {
      "id": "73143A089AC84FC28AD7F430329038B6",
      "asnIdentifier": null,
      "position": 1078,
      "depth": 2,
      "listId": "67",
      "statementNotation": "8.67",
      "altStatementNotation": null,
      "statementLabel": null,
      "description": "Propose and advocate for a specific method of action that can be taken by the federal government to best respond to a\ncurrent situation in which a country is at risk for genocide or mass atrocity.",
      "comments": [],
      "ancestorIds": [
        "1AAEB1A938DD47C58DF0E5ACAF302782",
        "C9E47DE89753450DBA0DD823DFA4E0AF"
      ],
      "parentId": "1AAEB1A938DD47C58DF0E5ACAF302782"
    },
    "3F5F881707764F7DB720FCD8F81C5A53": {
      "id": "3F5F881707764F7DB720FCD8F81C5A53",
      "asnIdentifier": null,
      "position": 1077,
      "depth": 2,
      "listId": "66",
      "statementNotation": "8.66",
      "altStatementNotation": null,
      "statementLabel": null,
      "description": "Evaluate the ways in which countries and international organizations recognize and respond to indications that a country is\nat risk for genocide or mass atrocity.",
      "comments": [],
      "ancestorIds": [
        "1AAEB1A938DD47C58DF0E5ACAF302782",
        "C9E47DE89753450DBA0DD823DFA4E0AF"
      ],
      "parentId": "1AAEB1A938DD47C58DF0E5ACAF302782"
    },
    "B84A7A324F844BA5913B2E613F8ED3E2": {
      "id": "B84A7A324F844BA5913B2E613F8ED3E2",
      "asnIdentifier": null,
      "position": 1076,
      "depth": 2,
      "listId": "65",
      "statementNotation": "8.65",
      "altStatementNotation": null,
      "statementLabel": null,
      "description": "Analyze the common risk factors and warning signs that indicate a country is at risk for genocide or mass atrocity and identify\nhow they have been present during the Holocaust and at least one other genocide.  ",
      "comments": [],
      "ancestorIds": [
        "1AAEB1A938DD47C58DF0E5ACAF302782",
        "C9E47DE89753450DBA0DD823DFA4E0AF"
      ],
      "parentId": "1AAEB1A938DD47C58DF0E5ACAF302782"
    },
    "F9B02464420B4EAEB6FDD94F77FFD0E4": {
      "id": "F9B02464420B4EAEB6FDD94F77FFD0E4",
      "asnIdentifier": null,
      "position": 1075,
      "depth": 2,
      "listId": "64",
      "statementNotation": "8.64",
      "altStatementNotation": null,
      "statementLabel": null,
      "description": "Compare the effectiveness of methods used by the United States government to enact foreign policy, including sanctions,\naid, diplomacy, military force, coalition building, and deterrence.",
      "comments": [],
      "ancestorIds": [
        "1AAEB1A938DD47C58DF0E5ACAF302782",
        "C9E47DE89753450DBA0DD823DFA4E0AF"
      ],
      "parentId": "1AAEB1A938DD47C58DF0E5ACAF302782"
    },
    "1F8C409C5CAA4B7AB63E3978F4B26CAA": {
      "id": "1F8C409C5CAA4B7AB63E3978F4B26CAA",
      "asnIdentifier": null,
      "position": 1074,
      "depth": 2,
      "listId": "63",
      "statementNotation": "8.63",
      "altStatementNotation": null,
      "statementLabel": null,
      "description": "Analyze the ways in which at least three different countries impact policy beyond their borders. ",
      "comments": [],
      "ancestorIds": [
        "1AAEB1A938DD47C58DF0E5ACAF302782",
        "C9E47DE89753450DBA0DD823DFA4E0AF"
      ],
      "parentId": "1AAEB1A938DD47C58DF0E5ACAF302782"
    },
    "1AAEB1A938DD47C58DF0E5ACAF302782": {
      "id": "1AAEB1A938DD47C58DF0E5ACAF302782",
      "asnIdentifier": null,
      "position": 1073,
      "depth": 1,
      "listId": "",
      "statementNotation": "",
      "altStatementNotation": null,
      "statementLabel": null,
      "description": "In this driving concept, students will evaluate the efficacy of different tools of foreign policy that different countries and the\nUnited States use to impact global change. Students will evaluate the factors that lead to mass atrocity such as global genocide.\nStudents should study different actions global citizens can take to address foreign crises and evaluate each action for its\neffectiveness. These standards are best taught using a case study approach in which students apply their understanding to a\nspecific global event and take action.",
      "comments": [],
      "ancestorIds": [
        "C9E47DE89753450DBA0DD823DFA4E0AF"
      ],
      "parentId": "C9E47DE89753450DBA0DD823DFA4E0AF"
    },
    "C9E47DE89753450DBA0DD823DFA4E0AF": {
      "id": "C9E47DE89753450DBA0DD823DFA4E0AF",
      "asnIdentifier": null,
      "position": 1072,
      "depth": 0,
      "listId": "7",
      "statementNotation": "",
      "altStatementNotation": null,
      "statementLabel": null,
      "description": "Driving Concept 7: Global Opportunities for Action",
      "comments": [],
      "ancestorIds": [],
      "parentId": null
    },
    "DB9E651CFBDC461990E79DAB6DDCFF37": {
      "id": "DB9E651CFBDC461990E79DAB6DDCFF37",
      "asnIdentifier": null,
      "position": 1071,
      "depth": 2,
      "listId": "62",
      "statementNotation": "8.62",
      "altStatementNotation": null,
      "statementLabel": null,
      "description": "Identify a local, national or international issue, assess options for taking action, and construct an action proposal designed\nto make change.",
      "comments": [],
      "ancestorIds": [
        "FEBF17724EF943A6BDE5C316CFC9C0E8",
        "94B25C573E0842C39336B895EC0669B7"
      ],
      "parentId": "FEBF17724EF943A6BDE5C316CFC9C0E8"
    },
    "2D15E92D99C8413BABA87AAD5285FD74": {
      "id": "2D15E92D99C8413BABA87AAD5285FD74",
      "asnIdentifier": null,
      "position": 1070,
      "depth": 2,
      "listId": "61",
      "statementNotation": "8.61",
      "altStatementNotation": null,
      "statementLabel": null,
      "description": "Evaluate the role and efficacy of civil disobedience, mass protest and strikes in creating change. ",
      "comments": [],
      "ancestorIds": [
        "FEBF17724EF943A6BDE5C316CFC9C0E8",
        "94B25C573E0842C39336B895EC0669B7"
      ],
      "parentId": "FEBF17724EF943A6BDE5C316CFC9C0E8"
    },
    "53836AE0B231460D819DA93A43CFE01E": {
      "id": "53836AE0B231460D819DA93A43CFE01E",
      "asnIdentifier": null,
      "position": 1069,
      "depth": 2,
      "listId": "60",
      "statementNotation": "8.60",
      "altStatementNotation": null,
      "statementLabel": null,
      "description": "Analyze an individual or a group involved in a historic or current protest movement to evaluate their efforts to achieve\nreform or improve society.",
      "comments": [],
      "ancestorIds": [
        "FEBF17724EF943A6BDE5C316CFC9C0E8",
        "94B25C573E0842C39336B895EC0669B7"
      ],
      "parentId": "FEBF17724EF943A6BDE5C316CFC9C0E8"
    },
    "176ACA853B5843F6956521F94094469C": {
      "id": "176ACA853B5843F6956521F94094469C",
      "asnIdentifier": null,
      "position": 1068,
      "depth": 2,
      "listId": "59",
      "statementNotation": "8.59",
      "altStatementNotation": null,
      "statementLabel": null,
      "description": "Evaluate the effectiveness of non-governmental organizations in Washington, DC at participating in and creating change.",
      "comments": [],
      "ancestorIds": [
        "FEBF17724EF943A6BDE5C316CFC9C0E8",
        "94B25C573E0842C39336B895EC0669B7"
      ],
      "parentId": "FEBF17724EF943A6BDE5C316CFC9C0E8"
    },
    "C5D29D0A6CB14BF28D9C3D5B6A8CEC3B": {
      "id": "C5D29D0A6CB14BF28D9C3D5B6A8CEC3B",
      "asnIdentifier": null,
      "position": 1067,
      "depth": 2,
      "listId": "58",
      "statementNotation": "8.58",
      "altStatementNotation": null,
      "statementLabel": null,
      "description": "Analyze the significance of Washington, DC as a historic and current location for national protests, rallies or other\ndemonstrations.",
      "comments": [],
      "ancestorIds": [
        "FEBF17724EF943A6BDE5C316CFC9C0E8",
        "94B25C573E0842C39336B895EC0669B7"
      ],
      "parentId": "FEBF17724EF943A6BDE5C316CFC9C0E8"
    },
    "9FF786D1D82D473D92953C96D59084EB": {
      "id": "9FF786D1D82D473D92953C96D59084EB",
      "asnIdentifier": null,
      "position": 1066,
      "depth": 2,
      "listId": "57",
      "statementNotation": "8.57",
      "altStatementNotation": null,
      "statementLabel": null,
      "description": "Evaluate lasting and short-term impacts of protests to economic, social and environmental policy.",
      "comments": [],
      "ancestorIds": [
        "FEBF17724EF943A6BDE5C316CFC9C0E8",
        "94B25C573E0842C39336B895EC0669B7"
      ],
      "parentId": "FEBF17724EF943A6BDE5C316CFC9C0E8"
    },
    "6B6294B9F2D44859A684455F4CB7894D": {
      "id": "6B6294B9F2D44859A684455F4CB7894D",
      "asnIdentifier": null,
      "position": 1065,
      "depth": 2,
      "listId": "56",
      "statementNotation": "8.56",
      "altStatementNotation": null,
      "statementLabel": null,
      "description": "Analyze the ways in which media and technology have been used as tools for resistance and protest.",
      "comments": [],
      "ancestorIds": [
        "FEBF17724EF943A6BDE5C316CFC9C0E8",
        "94B25C573E0842C39336B895EC0669B7"
      ],
      "parentId": "FEBF17724EF943A6BDE5C316CFC9C0E8"
    },
    "D66147829B8B4B85B231AB932AE16981": {
      "id": "D66147829B8B4B85B231AB932AE16981",
      "asnIdentifier": null,
      "position": 1064,
      "depth": 2,
      "listId": "55",
      "statementNotation": "8.55",
      "altStatementNotation": null,
      "statementLabel": null,
      "description": "Compare the tactics, strategies, leaders, major events and enduring impacts of at least two different social movements\nwithin the US.",
      "comments": [],
      "ancestorIds": [
        "FEBF17724EF943A6BDE5C316CFC9C0E8",
        "94B25C573E0842C39336B895EC0669B7"
      ],
      "parentId": "FEBF17724EF943A6BDE5C316CFC9C0E8"
    },
    "523C64E7E34F4618AC9C2C34A50773B3": {
      "id": "523C64E7E34F4618AC9C2C34A50773B3",
      "asnIdentifier": null,
      "position": 1063,
      "depth": 2,
      "listId": "54",
      "statementNotation": "8.54",
      "altStatementNotation": null,
      "statementLabel": null,
      "description": "Analyze how the First Amendment of the US Constitution has been interpreted to limit or provide opportunities for citizen\naction to protest, resist and influence government policy.",
      "comments": [],
      "ancestorIds": [
        "FEBF17724EF943A6BDE5C316CFC9C0E8",
        "94B25C573E0842C39336B895EC0669B7"
      ],
      "parentId": "FEBF17724EF943A6BDE5C316CFC9C0E8"
    },
    "98DD1C86C1AC4C859BF09F78F2175606": {
      "id": "98DD1C86C1AC4C859BF09F78F2175606",
      "asnIdentifier": null,
      "position": 1062,
      "depth": 2,
      "listId": "53",
      "statementNotation": "8.53",
      "altStatementNotation": null,
      "statementLabel": null,
      "description": "Analyze global examples of citizen action to enact change through protests and resistance to government action, and\nevaluate their success in achieving their stated purpose and the long-term effects of the action.",
      "comments": [],
      "ancestorIds": [
        "FEBF17724EF943A6BDE5C316CFC9C0E8",
        "94B25C573E0842C39336B895EC0669B7"
      ],
      "parentId": "FEBF17724EF943A6BDE5C316CFC9C0E8"
    },
    "FEBF17724EF943A6BDE5C316CFC9C0E8": {
      "id": "FEBF17724EF943A6BDE5C316CFC9C0E8",
      "asnIdentifier": null,
      "position": 1061,
      "depth": 1,
      "listId": "",
      "statementNotation": "",
      "altStatementNotation": null,
      "statementLabel": null,
      "description": "In this driving concept, students will understand how effective protest and resistance can lead to economic, political, and social\nchange. Students will analyze the challenges of engaging civic action at the local, national and global levels and evaluate the\neffects of civic action on public policy in the United States and other countries. Students should study the actions of groups who\nprotest and resist oppressive government actions, laws, or policies. These standards are best taught using a case study approach\nin which students apply their understanding to a specific policy issue",
      "comments": [],
      "ancestorIds": [
        "94B25C573E0842C39336B895EC0669B7"
      ],
      "parentId": "94B25C573E0842C39336B895EC0669B7"
    },
    "94B25C573E0842C39336B895EC0669B7": {
      "id": "94B25C573E0842C39336B895EC0669B7",
      "asnIdentifier": null,
      "position": 1060,
      "depth": 0,
      "listId": "6",
      "statementNotation": "",
      "altStatementNotation": null,
      "statementLabel": null,
      "description": "Driving Concept 6: Protest and Resistance",
      "comments": [],
      "ancestorIds": [],
      "parentId": null
    },
    "2FD32255F9D54517B2DD14CF0382F868": {
      "id": "2FD32255F9D54517B2DD14CF0382F868",
      "asnIdentifier": null,
      "position": 1058,
      "depth": 2,
      "listId": "52",
      "statementNotation": "8.52",
      "altStatementNotation": null,
      "statementLabel": null,
      "description": "Identify a local, national or international issue connected to access to power and representation, conduct relevant research,\nidentify and assess policy options, and construct a public policy proposal designed to improve the situation.",
      "comments": [],
      "ancestorIds": [
        "AF910C63AAD2416D986F65F935436CB6",
        "9C3749D7243345E2BB727DCDCA96AA52"
      ],
      "parentId": "AF910C63AAD2416D986F65F935436CB6"
    },
    "4F4A972CB3C94BA69A58320D8501D88F": {
      "id": "4F4A972CB3C94BA69A58320D8501D88F",
      "asnIdentifier": null,
      "position": 1057,
      "depth": 2,
      "listId": "51",
      "statementNotation": "8.51",
      "altStatementNotation": null,
      "statementLabel": null,
      "description": "Analyze the impact of urban geography and zoning on access to power and opportunity in Washington, DC.",
      "comments": [],
      "ancestorIds": [
        "AF910C63AAD2416D986F65F935436CB6",
        "9C3749D7243345E2BB727DCDCA96AA52"
      ],
      "parentId": "AF910C63AAD2416D986F65F935436CB6"
    },
    "E4D38D3CEB2A4F36954C04C10C250F23": {
      "id": "E4D38D3CEB2A4F36954C04C10C250F23",
      "asnIdentifier": null,
      "position": 1056,
      "depth": 2,
      "listId": "50",
      "statementNotation": "8.50",
      "altStatementNotation": null,
      "statementLabel": null,
      "description": "Identify and analyze opportunities to access political power in Washington, DC to initiate and support change.",
      "comments": [],
      "ancestorIds": [
        "AF910C63AAD2416D986F65F935436CB6",
        "9C3749D7243345E2BB727DCDCA96AA52"
      ],
      "parentId": "AF910C63AAD2416D986F65F935436CB6"
    },
    "E9657C8F41F94939B5780F03B90663C8": {
      "id": "E9657C8F41F94939B5780F03B90663C8",
      "asnIdentifier": null,
      "position": 1055,
      "depth": 2,
      "listId": "49",
      "statementNotation": "8.49",
      "altStatementNotation": null,
      "statementLabel": null,
      "description": "Evaluate the change in access to local and national power in Washington, DC over time and the impact of these changes on\nthe government of Washington, DC.",
      "comments": [],
      "ancestorIds": [
        "AF910C63AAD2416D986F65F935436CB6",
        "9C3749D7243345E2BB727DCDCA96AA52"
      ],
      "parentId": "AF910C63AAD2416D986F65F935436CB6"
    },
    "70FCEE6DB6EF4C16A4330F346273C967": {
      "id": "70FCEE6DB6EF4C16A4330F346273C967",
      "asnIdentifier": null,
      "position": 1054,
      "depth": 2,
      "listId": "48",
      "statementNotation": "8.48",
      "altStatementNotation": null,
      "statementLabel": null,
      "description": "8 Analyze the way in which national or local policy has shaped access to resources and opportunity or increased exposure to\nharmful environmental effects and how people have sought to address this.",
      "comments": [],
      "ancestorIds": [
        "AF910C63AAD2416D986F65F935436CB6",
        "9C3749D7243345E2BB727DCDCA96AA52"
      ],
      "parentId": "AF910C63AAD2416D986F65F935436CB6"
    },
    "9339C92FEC274559816B4C35BB348203": {
      "id": "9339C92FEC274559816B4C35BB348203",
      "asnIdentifier": null,
      "position": 1053,
      "depth": 2,
      "listId": "47",
      "statementNotation": "8.47",
      "altStatementNotation": null,
      "statementLabel": null,
      "description": "Compare 21st-century voter suppression to voter suppression in previous centuries, and analyze the historic, racialized, and\neconomic effects of voter suppression on various groups.",
      "comments": [],
      "ancestorIds": [
        "AF910C63AAD2416D986F65F935436CB6",
        "9C3749D7243345E2BB727DCDCA96AA52"
      ],
      "parentId": "AF910C63AAD2416D986F65F935436CB6"
    },
    "212A511E1F934752BC0D6B44C78BB1EF": {
      "id": "212A511E1F934752BC0D6B44C78BB1EF",
      "asnIdentifier": null,
      "position": 1052,
      "depth": 2,
      "listId": "46",
      "statementNotation": "8.46",
      "altStatementNotation": null,
      "statementLabel": null,
      "description": "Compare the ability of different individuals and public and private interest groups to influence public policy",
      "comments": [],
      "ancestorIds": [
        "AF910C63AAD2416D986F65F935436CB6",
        "9C3749D7243345E2BB727DCDCA96AA52"
      ],
      "parentId": "AF910C63AAD2416D986F65F935436CB6"
    },
    "8CFE7A94118C4A0DADDAB6145DD63DDA": {
      "id": "8CFE7A94118C4A0DADDAB6145DD63DDA",
      "asnIdentifier": null,
      "position": 1051,
      "depth": 2,
      "listId": "45",
      "statementNotation": "8.45",
      "altStatementNotation": null,
      "statementLabel": null,
      "description": "Evaluate the impact of the federal system and the structure of the federal government on the abilities of individuals in\ndifferent states, territories and Indigenous Nations to influence national policy.",
      "comments": [],
      "ancestorIds": [
        "AF910C63AAD2416D986F65F935436CB6",
        "9C3749D7243345E2BB727DCDCA96AA52"
      ],
      "parentId": "AF910C63AAD2416D986F65F935436CB6"
    },
    "098EF6B3BF804DCB9983115E85E86341": {
      "id": "098EF6B3BF804DCB9983115E85E86341",
      "asnIdentifier": null,
      "position": 1050,
      "depth": 2,
      "listId": "44",
      "statementNotation": "8.44",
      "altStatementNotation": null,
      "statementLabel": null,
      "description": "Analyze how international alliances and agreements (e.g., the United Nations, North Atlantic Treaty Organization, North\nAmerican Free Trade Agreement, International Monetary Fund, treaties with Indigenous Nations,) expand and limit people’s\naccess to power around the world.",
      "comments": [],
      "ancestorIds": [
        "AF910C63AAD2416D986F65F935436CB6",
        "9C3749D7243345E2BB727DCDCA96AA52"
      ],
      "parentId": "AF910C63AAD2416D986F65F935436CB6"
    },
    "AF910C63AAD2416D986F65F935436CB6": {
      "id": "AF910C63AAD2416D986F65F935436CB6",
      "asnIdentifier": null,
      "position": 1049,
      "depth": 1,
      "listId": "",
      "statementNotation": "",
      "altStatementNotation": null,
      "statementLabel": null,
      "description": "Through this driving concept, students will think critically about how power and the access to power have shaped public policy\nand societal experiences from a global, national and local perspective. Students will analyze the impact of race, gender, religion,\nethnicity and socio-economic status on access to power locally and globally. Students will evaluate the relationship between the\npeople and government, identifying, acknowledging, and solving real-world issues. Throughout this driving concept, students\nshould evaluate a specific public policy case, such as environmental policy, through the lens of power and create a proposal for\ntaking action.",
      "comments": [],
      "ancestorIds": [
        "9C3749D7243345E2BB727DCDCA96AA52"
      ],
      "parentId": "9C3749D7243345E2BB727DCDCA96AA52"
    },
    "9C3749D7243345E2BB727DCDCA96AA52": {
      "id": "9C3749D7243345E2BB727DCDCA96AA52",
      "asnIdentifier": null,
      "position": 1048,
      "depth": 0,
      "listId": "5",
      "statementNotation": "",
      "altStatementNotation": null,
      "statementLabel": null,
      "description": "Driving Concept 5: Power and Access to Power in Society",
      "comments": [],
      "ancestorIds": [],
      "parentId": null
    },
    "AE08F86635314EDEADE12E868C59185F": {
      "id": "AE08F86635314EDEADE12E868C59185F",
      "asnIdentifier": null,
      "position": 1048,
      "depth": 2,
      "listId": "43",
      "statementNotation": "8.43",
      "altStatementNotation": null,
      "statementLabel": null,
      "description": "Identify a local, national or international issue connected to human rights, conduct relevant research, identify and assess\npolicy options to address the issue, and construct a public policy proposal designed to improve the situation.",
      "comments": [],
      "ancestorIds": [
        "A1940F41DFE6496185EA5EB4475841AC",
        "4FAB1A5600444E34BDF502D0CE0C7371"
      ],
      "parentId": "A1940F41DFE6496185EA5EB4475841AC"
    },
    "C74B917C998242E5A57593062AB9AB34": {
      "id": "C74B917C998242E5A57593062AB9AB34",
      "asnIdentifier": null,
      "position": 1047,
      "depth": 2,
      "listId": "42",
      "statementNotation": "8.42",
      "altStatementNotation": null,
      "statementLabel": null,
      "description": "Evaluate the status of Washington, DC in the federal government, the impact on the rights of the citizens and residents of the\nDistrict and the movement for DC statehood.",
      "comments": [],
      "ancestorIds": [
        "A1940F41DFE6496185EA5EB4475841AC",
        "4FAB1A5600444E34BDF502D0CE0C7371"
      ],
      "parentId": "A1940F41DFE6496185EA5EB4475841AC"
    },
    "23F26F6662C142C2AC11B13B7BCE2836": {
      "id": "23F26F6662C142C2AC11B13B7BCE2836",
      "asnIdentifier": null,
      "position": 1046,
      "depth": 2,
      "listId": "41",
      "statementNotation": "8.41",
      "altStatementNotation": null,
      "statementLabel": null,
      "description": "Evaluate contemporary debates about the proper application of the rights reserved through the Bill of Rights, and develop a\nproposal for personal or collective action to address the issue.",
      "comments": [],
      "ancestorIds": [
        "A1940F41DFE6496185EA5EB4475841AC",
        "4FAB1A5600444E34BDF502D0CE0C7371"
      ],
      "parentId": "A1940F41DFE6496185EA5EB4475841AC"
    },
    "784802C88D88453880C1A8DDC776E2DB": {
      "id": "784802C88D88453880C1A8DDC776E2DB",
      "asnIdentifier": null,
      "position": 1045,
      "depth": 2,
      "listId": "40",
      "statementNotation": "8.40",
      "altStatementNotation": null,
      "statementLabel": null,
      "description": "Evaluate contemporary debates about the proper enforcement of the 13th, 14th and 15th Amendments",
      "comments": [],
      "ancestorIds": [
        "A1940F41DFE6496185EA5EB4475841AC",
        "4FAB1A5600444E34BDF502D0CE0C7371"
      ],
      "parentId": "A1940F41DFE6496185EA5EB4475841AC"
    },
    "4BC09F8B9E224AFD940BA988D6AA317F": {
      "id": "4BC09F8B9E224AFD940BA988D6AA317F",
      "asnIdentifier": null,
      "position": 1044,
      "depth": 2,
      "listId": "39",
      "statementNotation": "8.39",
      "altStatementNotation": null,
      "statementLabel": null,
      "description": "Analyze a current economic issue that curtails or infringes on the rights of individuals and groups and offer alternative\napproaches to address the needs of different individuals, groups and society.",
      "comments": [],
      "ancestorIds": [
        "A1940F41DFE6496185EA5EB4475841AC",
        "4FAB1A5600444E34BDF502D0CE0C7371"
      ],
      "parentId": "A1940F41DFE6496185EA5EB4475841AC"
    },
    "99855C712E634A1E842352215C6D46DF": {
      "id": "99855C712E634A1E842352215C6D46DF",
      "asnIdentifier": null,
      "position": 1043,
      "depth": 2,
      "listId": "38",
      "statementNotation": "8.38",
      "altStatementNotation": null,
      "statementLabel": null,
      "description": "Evaluate the ways different activist groups have used the court system to expand or limit the rights of different individuals\nand groups.",
      "comments": [],
      "ancestorIds": [
        "A1940F41DFE6496185EA5EB4475841AC",
        "4FAB1A5600444E34BDF502D0CE0C7371"
      ],
      "parentId": "A1940F41DFE6496185EA5EB4475841AC"
    },
    "39134438A1AE43C3BF08FDA0E9341AFE": {
      "id": "39134438A1AE43C3BF08FDA0E9341AFE",
      "asnIdentifier": null,
      "position": 1042,
      "depth": 2,
      "listId": "37",
      "statementNotation": "8.37",
      "altStatementNotation": null,
      "statementLabel": null,
      "description": "Analyze at least 3 historic Supreme Court cases that establish, extend or limit the rights of individuals.",
      "comments": [],
      "ancestorIds": [
        "A1940F41DFE6496185EA5EB4475841AC",
        "4FAB1A5600444E34BDF502D0CE0C7371"
      ],
      "parentId": "A1940F41DFE6496185EA5EB4475841AC"
    },
    "D0F707A03D2743A99C3AB28EB483307B": {
      "id": "D0F707A03D2743A99C3AB28EB483307B",
      "asnIdentifier": null,
      "position": 1041,
      "depth": 2,
      "listId": "36",
      "statementNotation": "8.36",
      "altStatementNotation": null,
      "statementLabel": null,
      "description": "Identify the rights of individuals and groups codified in the US Constitution, and evaluate the extent to which those rights\nhave been realized.",
      "comments": [],
      "ancestorIds": [
        "A1940F41DFE6496185EA5EB4475841AC",
        "4FAB1A5600444E34BDF502D0CE0C7371"
      ],
      "parentId": "A1940F41DFE6496185EA5EB4475841AC"
    },
    "8724CBD33118462A9296AB0C721BA8B4": {
      "id": "8724CBD33118462A9296AB0C721BA8B4",
      "asnIdentifier": null,
      "position": 1040,
      "depth": 2,
      "listId": "35",
      "statementNotation": "8.35",
      "altStatementNotation": null,
      "statementLabel": null,
      "description": "Analyze the history of the Universal Declaration of Human Rights and the rights enumerated in the document.",
      "comments": [],
      "ancestorIds": [
        "A1940F41DFE6496185EA5EB4475841AC",
        "4FAB1A5600444E34BDF502D0CE0C7371"
      ],
      "parentId": "A1940F41DFE6496185EA5EB4475841AC"
    },
    "3A369BAD64AD494583C13E551831C51C": {
      "id": "3A369BAD64AD494583C13E551831C51C",
      "asnIdentifier": null,
      "position": 1039,
      "depth": 2,
      "listId": "34",
      "statementNotation": "8.34",
      "altStatementNotation": null,
      "statementLabel": null,
      "description": "Analyze the rights of citizens in at least three countries around the world and how the government upholds or violates these\nrights, and evaluate the extent to which the public has the ability to influence the decision-making of different governments\nglobally.",
      "comments": [],
      "ancestorIds": [
        "A1940F41DFE6496185EA5EB4475841AC",
        "4FAB1A5600444E34BDF502D0CE0C7371"
      ],
      "parentId": "A1940F41DFE6496185EA5EB4475841AC"
    },
    "A1940F41DFE6496185EA5EB4475841AC": {
      "id": "A1940F41DFE6496185EA5EB4475841AC",
      "asnIdentifier": null,
      "position": 1038,
      "depth": 1,
      "listId": "",
      "statementNotation": "",
      "altStatementNotation": null,
      "statementLabel": null,
      "description": "Through this driving concept, students will investigate the ways in which governments attempt to balance individual rights with\npublic safety and order. Students should compare the different rights and protections of citizens around the world with the\nrights and protections provided by the United States government. Students should analyze the reasons for the evolution of rights\nover time, including the broadening definition of “citizen,” and evaluate the reasons different groups have been excluded from\nconstitutional protections over time. Students should also evaluate the rights of District residents. Throughout this driving\nconcept, students should evaluate a specific public policy case through the lens of rights and create a proposal for taking action.",
      "comments": [],
      "ancestorIds": [
        "4FAB1A5600444E34BDF502D0CE0C7371"
      ],
      "parentId": "4FAB1A5600444E34BDF502D0CE0C7371"
    },
    "4FAB1A5600444E34BDF502D0CE0C7371": {
      "id": "4FAB1A5600444E34BDF502D0CE0C7371",
      "asnIdentifier": null,
      "position": 1037,
      "depth": 0,
      "listId": "4",
      "statementNotation": "",
      "altStatementNotation": null,
      "statementLabel": null,
      "description": "Driving Concept 4: Rights of the People",
      "comments": [],
      "ancestorIds": [],
      "parentId": null
    },
    "0459171A9C5946C4B841C73968EE9203": {
      "id": "0459171A9C5946C4B841C73968EE9203",
      "asnIdentifier": null,
      "position": 1037,
      "depth": 2,
      "listId": "33",
      "statementNotation": "8.33",
      "altStatementNotation": null,
      "statementLabel": null,
      "description": "Develop a plan to use technology and online platforms for civic engagement and to drive social change.",
      "comments": [],
      "ancestorIds": [
        "0D4AF3392D8340D39EE8F2ACB247AE73",
        "1780A382ED3049E69D20D84E56F3376D"
      ],
      "parentId": "0D4AF3392D8340D39EE8F2ACB247AE73"
    },
    "A558E187AB2E4CE8A148BC1A00135FB9": {
      "id": "A558E187AB2E4CE8A148BC1A00135FB9",
      "asnIdentifier": null,
      "position": 1037,
      "depth": 2,
      "listId": "32",
      "statementNotation": "8.32",
      "altStatementNotation": null,
      "statementLabel": null,
      "description": "Critically evaluate price, product claims, and quality of information from a variety of sources to make informed consumer\ndecisions.",
      "comments": [],
      "ancestorIds": [
        "0D4AF3392D8340D39EE8F2ACB247AE73",
        "1780A382ED3049E69D20D84E56F3376D"
      ],
      "parentId": "0D4AF3392D8340D39EE8F2ACB247AE73"
    },
    "8177913B78DB499E8E3D5870B317B031": {
      "id": "8177913B78DB499E8E3D5870B317B031",
      "asnIdentifier": null,
      "position": 1036,
      "depth": 2,
      "listId": "31",
      "statementNotation": "8.31",
      "altStatementNotation": null,
      "statementLabel": null,
      "description": "Analyze the role of social media in shaping political ideology, framing policy debates, and accurately informing the public\nabout major policy issues within the United States.",
      "comments": [],
      "ancestorIds": [
        "0D4AF3392D8340D39EE8F2ACB247AE73",
        "1780A382ED3049E69D20D84E56F3376D"
      ],
      "parentId": "0D4AF3392D8340D39EE8F2ACB247AE73"
    },
    "0A147B47566A4708A7938666012C5663": {
      "id": "0A147B47566A4708A7938666012C5663",
      "asnIdentifier": null,
      "position": 1035,
      "depth": 2,
      "listId": "30",
      "statementNotation": "8.30",
      "altStatementNotation": null,
      "statementLabel": null,
      "description": "Analyze historical examples of using art or mass media to successfully influence public policy outcomes.",
      "comments": [],
      "ancestorIds": [
        "0D4AF3392D8340D39EE8F2ACB247AE73",
        "1780A382ED3049E69D20D84E56F3376D"
      ],
      "parentId": "0D4AF3392D8340D39EE8F2ACB247AE73"
    },
    "17FE17A62A494606B4BFA7000BCE7FC9": {
      "id": "17FE17A62A494606B4BFA7000BCE7FC9",
      "asnIdentifier": null,
      "position": 1034,
      "depth": 2,
      "listId": "29",
      "statementNotation": "8.29",
      "altStatementNotation": null,
      "statementLabel": null,
      "description": "Evaluate the strengths and weaknesses of traditional news media organizations (newspapers, magazines, and television) in\ncreating an informed public, including an analysis of the use of fact checkers, editors, framing and focus. ",
      "comments": [],
      "ancestorIds": [
        "0D4AF3392D8340D39EE8F2ACB247AE73",
        "1780A382ED3049E69D20D84E56F3376D"
      ],
      "parentId": "0D4AF3392D8340D39EE8F2ACB247AE73"
    },
    "25895116D58D492584C5B5DE1079AD88": {
      "id": "25895116D58D492584C5B5DE1079AD88",
      "asnIdentifier": null,
      "position": 1033,
      "depth": 2,
      "listId": "28",
      "statementNotation": "8.28",
      "altStatementNotation": null,
      "statementLabel": null,
      "description": "Compare multiple accounts from different news or media sources about an issue of concern",
      "comments": [],
      "ancestorIds": [
        "0D4AF3392D8340D39EE8F2ACB247AE73",
        "1780A382ED3049E69D20D84E56F3376D"
      ],
      "parentId": "0D4AF3392D8340D39EE8F2ACB247AE73"
    },
    "65E655BA5DD64A9ABEBFE6F044518375": {
      "id": "65E655BA5DD64A9ABEBFE6F044518375",
      "asnIdentifier": null,
      "position": 1032,
      "depth": 2,
      "listId": "27",
      "statementNotation": "8.27",
      "altStatementNotation": null,
      "statementLabel": null,
      "description": "Analyze the point of view and evaluate the claims of an editorial, editorial cartoon or op-ed commentary on a public policy\nissue at the local, state or national level.",
      "comments": [],
      "ancestorIds": [
        "0D4AF3392D8340D39EE8F2ACB247AE73",
        "1780A382ED3049E69D20D84E56F3376D"
      ],
      "parentId": "0D4AF3392D8340D39EE8F2ACB247AE73"
    },
    "E5D721D03E244AE0B5D5E6CA21F04347": {
      "id": "E5D721D03E244AE0B5D5E6CA21F04347",
      "asnIdentifier": null,
      "position": 1031,
      "depth": 2,
      "listId": "26",
      "statementNotation": "8.26",
      "altStatementNotation": null,
      "statementLabel": null,
      "description": "Identify resources to reference (e.g., fact checking and news organizations) while evaluating online sources and claims.",
      "comments": [],
      "ancestorIds": [
        "0D4AF3392D8340D39EE8F2ACB247AE73",
        "1780A382ED3049E69D20D84E56F3376D"
      ],
      "parentId": "0D4AF3392D8340D39EE8F2ACB247AE73"
    },
    "E52E72C8A15C41229662B539914B301F": {
      "id": "E52E72C8A15C41229662B539914B301F",
      "asnIdentifier": null,
      "position": 1030,
      "depth": 2,
      "listId": "25",
      "statementNotation": "8.25",
      "altStatementNotation": null,
      "statementLabel": null,
      "description": "Evaluate the accuracy of a range of claims made by digital sources through lateral reading when information about the\nsource is unavailable.",
      "comments": [],
      "ancestorIds": [
        "0D4AF3392D8340D39EE8F2ACB247AE73",
        "1780A382ED3049E69D20D84E56F3376D"
      ],
      "parentId": "0D4AF3392D8340D39EE8F2ACB247AE73"
    },
    "3FFEC1CD01E64D2DA288CD2EF3D560AC": {
      "id": "3FFEC1CD01E64D2DA288CD2EF3D560AC",
      "asnIdentifier": null,
      "position": 1029,
      "depth": 2,
      "listId": "24",
      "statementNotation": "8.24",
      "altStatementNotation": null,
      "statementLabel": null,
      "description": "Evaluate the credibility of a range of digital sources using civic online reasoning strategies including lateral reading and click\nrestraint.",
      "comments": [],
      "ancestorIds": [
        "0D4AF3392D8340D39EE8F2ACB247AE73",
        "1780A382ED3049E69D20D84E56F3376D"
      ],
      "parentId": "0D4AF3392D8340D39EE8F2ACB247AE73"
    },
    "240A65ACDB524125AF3F17A7D45CBF69": {
      "id": "240A65ACDB524125AF3F17A7D45CBF69",
      "asnIdentifier": null,
      "position": 1028,
      "depth": 2,
      "listId": "23",
      "statementNotation": "8.23",
      "altStatementNotation": null,
      "statementLabel": null,
      "description": "Compare the ways in which individuals in at least three different countries around the world receive information, including\nan analysis of the relationship between different governments and media",
      "comments": [],
      "ancestorIds": [
        "0D4AF3392D8340D39EE8F2ACB247AE73",
        "1780A382ED3049E69D20D84E56F3376D"
      ],
      "parentId": "0D4AF3392D8340D39EE8F2ACB247AE73"
    },
    "0D4AF3392D8340D39EE8F2ACB247AE73": {
      "id": "0D4AF3392D8340D39EE8F2ACB247AE73",
      "asnIdentifier": null,
      "position": 1027,
      "depth": 1,
      "listId": "",
      "statementNotation": "",
      "altStatementNotation": null,
      "statementLabel": null,
      "description": "This driving concept will engage students in a critical analysis of the role of media and social media in shaping the understanding\nand narrative of a policy question. Students will understand how to use media to investigate a contemporary issue and how to\ninvestigate the reliability of a website or organization. Students will understand how to evaluate coverage, framing and missing\nviewpoints in traditional news sources. This driving concept is best explored through explicit instruction in digital literacy\nstrategies and practice with curated materials.",
      "comments": [],
      "ancestorIds": [
        "1780A382ED3049E69D20D84E56F3376D"
      ],
      "parentId": "1780A382ED3049E69D20D84E56F3376D"
    },
    "1780A382ED3049E69D20D84E56F3376D": {
      "id": "1780A382ED3049E69D20D84E56F3376D",
      "asnIdentifier": null,
      "position": 1026,
      "depth": 0,
      "listId": "3",
      "statementNotation": "",
      "altStatementNotation": null,
      "statementLabel": null,
      "description": "Driving Concept 3: Media, Society, Government, and Digital Literacy",
      "comments": [],
      "ancestorIds": [],
      "parentId": null
    },
    "AFE780D8FA79466CB40F0A8ED27D5B9A": {
      "id": "AFE780D8FA79466CB40F0A8ED27D5B9A",
      "asnIdentifier": null,
      "position": 1025,
      "depth": 2,
      "listId": "22",
      "statementNotation": "8.22",
      "altStatementNotation": null,
      "statementLabel": null,
      "description": "Propose and advocate for specific changes to the structure and function of federal or local government to best meet the\nneeds of the people, and/or propose a specific way to best create change within the current system.",
      "comments": [],
      "ancestorIds": [
        "2DD9349FCBBE4FD38AF9E760CE735A39",
        "E9793A0BDB2F45578C8639D1BC8B19E6"
      ],
      "parentId": "2DD9349FCBBE4FD38AF9E760CE735A39"
    },
    "01B268CC963C495B9695FB115EAC5A1D": {
      "id": "01B268CC963C495B9695FB115EAC5A1D",
      "asnIdentifier": null,
      "position": 1024,
      "depth": 2,
      "listId": "21",
      "statementNotation": "8.21",
      "altStatementNotation": null,
      "statementLabel": null,
      "description": "Evaluate the effectiveness of the structure and functions of the Washington, DC government in enacting policies that are\nreflective of community concerns.",
      "comments": [],
      "ancestorIds": [
        "2DD9349FCBBE4FD38AF9E760CE735A39",
        "E9793A0BDB2F45578C8639D1BC8B19E6"
      ],
      "parentId": "2DD9349FCBBE4FD38AF9E760CE735A39"
    },
    "0986D3123969497B9D418D1E8783F1D4": {
      "id": "0986D3123969497B9D418D1E8783F1D4",
      "asnIdentifier": null,
      "position": 1023,
      "depth": 2,
      "listId": "20",
      "statementNotation": "8.20",
      "altStatementNotation": null,
      "statementLabel": null,
      "description": "Evaluate the extent to which the interests of Washington, DC residents are represented in the federal government and\nevaluate the impact of the relationship between the District and the federal government on local policy.",
      "comments": [],
      "ancestorIds": [
        "2DD9349FCBBE4FD38AF9E760CE735A39",
        "E9793A0BDB2F45578C8639D1BC8B19E6"
      ],
      "parentId": "2DD9349FCBBE4FD38AF9E760CE735A39"
    },
    "3A6C79F40D854B9189DA348C48E1952D": {
      "id": "3A6C79F40D854B9189DA348C48E1952D",
      "asnIdentifier": null,
      "position": 1022,
      "depth": 2,
      "listId": "19",
      "statementNotation": "8.19",
      "altStatementNotation": null,
      "statementLabel": null,
      "description": "Explain the structure and powers of the Washington, DC government, including the features of the Executive, Legislative\nand Judicial branches.",
      "comments": [],
      "ancestorIds": [
        "2DD9349FCBBE4FD38AF9E760CE735A39",
        "E9793A0BDB2F45578C8639D1BC8B19E6"
      ],
      "parentId": "2DD9349FCBBE4FD38AF9E760CE735A39"
    },
    "7BA80A2EFA8E4126BA1AA33D946440CA": {
      "id": "7BA80A2EFA8E4126BA1AA33D946440CA",
      "asnIdentifier": null,
      "position": 1021,
      "depth": 2,
      "listId": "18",
      "statementNotation": "8.18",
      "altStatementNotation": null,
      "statementLabel": null,
      "description": "Assess the responsiveness of elected federal officials in enacting policies reflective of national public concerns and interests.",
      "comments": [],
      "ancestorIds": [
        "2DD9349FCBBE4FD38AF9E760CE735A39",
        "E9793A0BDB2F45578C8639D1BC8B19E6"
      ],
      "parentId": "2DD9349FCBBE4FD38AF9E760CE735A39"
    },
    "E19249B87C1E451CAAFCDEE58592FED5": {
      "id": "E19249B87C1E451CAAFCDEE58592FED5",
      "asnIdentifier": null,
      "position": 1020,
      "depth": 2,
      "listId": "17",
      "statementNotation": "8.17",
      "altStatementNotation": null,
      "statementLabel": null,
      "description": "Evaluate the efficacy of different government policies in helping individuals increase their personal savings and economic\nresilience.",
      "comments": [],
      "ancestorIds": [
        "2DD9349FCBBE4FD38AF9E760CE735A39",
        "E9793A0BDB2F45578C8639D1BC8B19E6"
      ],
      "parentId": "2DD9349FCBBE4FD38AF9E760CE735A39"
    },
    "D9E4C8613A4C4ED796150D622747F343": {
      "id": "D9E4C8613A4C4ED796150D622747F343",
      "asnIdentifier": null,
      "position": 1019,
      "depth": 2,
      "listId": "16",
      "statementNotation": "8.16",
      "altStatementNotation": null,
      "statementLabel": null,
      "description": "Identify elected leaders in the legislative and executive branches of the federal and local governments and identify multiple\nways for citizens to contact government officials to advocate for legislation or public policy. ",
      "comments": [],
      "ancestorIds": [
        "2DD9349FCBBE4FD38AF9E760CE735A39",
        "E9793A0BDB2F45578C8639D1BC8B19E6"
      ],
      "parentId": "2DD9349FCBBE4FD38AF9E760CE735A39"
    },
    "424D878FA6DE4BEEA0FCCEF4C5F9B81D": {
      "id": "424D878FA6DE4BEEA0FCCEF4C5F9B81D",
      "asnIdentifier": null,
      "position": 1018,
      "depth": 2,
      "listId": "15",
      "statementNotation": "8.15",
      "altStatementNotation": null,
      "statementLabel": null,
      "description": "Analyze a current Supreme Court ruling to understand the role of the court system in the United States.",
      "comments": [],
      "ancestorIds": [
        "2DD9349FCBBE4FD38AF9E760CE735A39",
        "E9793A0BDB2F45578C8639D1BC8B19E6"
      ],
      "parentId": "2DD9349FCBBE4FD38AF9E760CE735A39"
    },
    "9CDDDBA10B1A45F79096966882A7E759": {
      "id": "9CDDDBA10B1A45F79096966882A7E759",
      "asnIdentifier": null,
      "position": 1017,
      "depth": 2,
      "listId": "14",
      "statementNotation": "8.14",
      "altStatementNotation": null,
      "statementLabel": null,
      "description": "Analyze a historic or current executive action to evaluate the power and limitations of presidential executive orders. ",
      "comments": [],
      "ancestorIds": [
        "2DD9349FCBBE4FD38AF9E760CE735A39",
        "E9793A0BDB2F45578C8639D1BC8B19E6"
      ],
      "parentId": "2DD9349FCBBE4FD38AF9E760CE735A39"
    },
    "2A103737CF944E5899DA4EB3BF0578AF": {
      "id": "2A103737CF944E5899DA4EB3BF0578AF",
      "asnIdentifier": null,
      "position": 1016,
      "depth": 2,
      "listId": "13",
      "statementNotation": "8.13",
      "altStatementNotation": null,
      "statementLabel": null,
      "description": "Analyze a historic or current piece of legislation or law such as the Americans with Disabilities Act (ADA) to evaluate the role\nof citizens, interest groups, and corporations, as well as elected leaders, in the legislative process.",
      "comments": [],
      "ancestorIds": [
        "2DD9349FCBBE4FD38AF9E760CE735A39",
        "E9793A0BDB2F45578C8639D1BC8B19E6"
      ],
      "parentId": "2DD9349FCBBE4FD38AF9E760CE735A39"
    },
    "9C9B82416B7F471BBDDDADD8D9065C16": {
      "id": "9C9B82416B7F471BBDDDADD8D9065C16",
      "asnIdentifier": null,
      "position": 1015,
      "depth": 2,
      "listId": "12",
      "statementNotation": "8.12",
      "altStatementNotation": null,
      "statementLabel": null,
      "description": "Analyze how a historic or current piece of legislation or law such as the Americans with Disabilities Act (ADA) impacts\ncitizens.",
      "comments": [],
      "ancestorIds": [
        "2DD9349FCBBE4FD38AF9E760CE735A39",
        "E9793A0BDB2F45578C8639D1BC8B19E6"
      ],
      "parentId": "2DD9349FCBBE4FD38AF9E760CE735A39"
    },
    "C102952DD8614EA697FCCE9ED6E3B0F1": {
      "id": "C102952DD8614EA697FCCE9ED6E3B0F1",
      "asnIdentifier": null,
      "position": 1014,
      "depth": 2,
      "listId": "11",
      "statementNotation": "8.11",
      "altStatementNotation": null,
      "statementLabel": null,
      "description": "Explain how a bill becomes a law in the federal government and evaluate the efficacy of the current system.",
      "comments": [],
      "ancestorIds": [
        "2DD9349FCBBE4FD38AF9E760CE735A39",
        "E9793A0BDB2F45578C8639D1BC8B19E6"
      ],
      "parentId": "2DD9349FCBBE4FD38AF9E760CE735A39"
    },
    "78313F2D32F84B729C3C3BE879697918": {
      "id": "78313F2D32F84B729C3C3BE879697918",
      "asnIdentifier": null,
      "position": 1013,
      "depth": 2,
      "listId": "10",
      "statementNotation": "8.10",
      "altStatementNotation": null,
      "statementLabel": null,
      "description": "Analyze the structures and functions of the three branches of the US federal government.",
      "comments": [],
      "ancestorIds": [
        "2DD9349FCBBE4FD38AF9E760CE735A39",
        "E9793A0BDB2F45578C8639D1BC8B19E6"
      ],
      "parentId": "2DD9349FCBBE4FD38AF9E760CE735A39"
    },
    "3320F11F5C3A4E93AEA076265996FE0B": {
      "id": "3320F11F5C3A4E93AEA076265996FE0B",
      "asnIdentifier": null,
      "position": 1012,
      "depth": 2,
      "listId": "9",
      "statementNotation": "8.9",
      "altStatementNotation": null,
      "statementLabel": null,
      "description": "Evaluate and compare the structures of government across three different countries or Indigenous Nations.",
      "comments": [],
      "ancestorIds": [
        "2DD9349FCBBE4FD38AF9E760CE735A39",
        "E9793A0BDB2F45578C8639D1BC8B19E6"
      ],
      "parentId": "2DD9349FCBBE4FD38AF9E760CE735A39"
    },
    "2DD9349FCBBE4FD38AF9E760CE735A39": {
      "id": "2DD9349FCBBE4FD38AF9E760CE735A39",
      "asnIdentifier": null,
      "position": 1011,
      "depth": 1,
      "listId": "",
      "statementNotation": "",
      "altStatementNotation": null,
      "statementLabel": null,
      "description": "This driving concept uses inquiry to engage students in a critical analysis of ways different governments around the world and\nwithin the US function. Students should compare the different ways in which governments around the world create and enforce\nlaws to the ways in which the United States creates and enforces laws. Students should also evaluate the ways that the local\ngovernment provides goods and services to residents of the District. Throughout this driving concept, students should evaluate a\nspecific public policy case and create a proposal advocating for the benefits of the current system, or propose a change that\nwould improve the ways in which the federal or local government meets the needs of residents.",
      "comments": [],
      "ancestorIds": [
        "E9793A0BDB2F45578C8639D1BC8B19E6"
      ],
      "parentId": "E9793A0BDB2F45578C8639D1BC8B19E6"
    },
    "E9793A0BDB2F45578C8639D1BC8B19E6": {
      "id": "E9793A0BDB2F45578C8639D1BC8B19E6",
      "asnIdentifier": null,
      "position": 1010,
      "depth": 0,
      "listId": "2",
      "statementNotation": "",
      "altStatementNotation": null,
      "statementLabel": null,
      "description": "Driving Concept 2: How does the Government Function?",
      "comments": [],
      "ancestorIds": [],
      "parentId": null
    },
    "367CDCC774884FB3B8C9668B260960FD": {
      "id": "367CDCC774884FB3B8C9668B260960FD",
      "asnIdentifier": null,
      "position": 1009,
      "depth": 2,
      "listId": "8",
      "statementNotation": "8.8",
      "altStatementNotation": null,
      "statementLabel": null,
      "description": "Construct a claim about the role of the government in the lives of citizens and residents of the United States.",
      "comments": [],
      "ancestorIds": [
        "D5D9B2C7354D4D3D90CA9389A4A8527B",
        "E35DF215E3134317BFBD60B5CA881084"
      ],
      "parentId": "D5D9B2C7354D4D3D90CA9389A4A8527B"
    },
    "6B13FA20C64842B39C51C63AC71EC524": {
      "id": "6B13FA20C64842B39C51C63AC71EC524",
      "asnIdentifier": null,
      "position": 1008,
      "depth": 2,
      "listId": "7",
      "statementNotation": "8.7",
      "altStatementNotation": null,
      "statementLabel": null,
      "description": "Analyze the role of the Washington, DC government over time including its power to enact policy to address economic, social\nand political problems. ",
      "comments": [],
      "ancestorIds": [
        "D5D9B2C7354D4D3D90CA9389A4A8527B",
        "E35DF215E3134317BFBD60B5CA881084"
      ],
      "parentId": "D5D9B2C7354D4D3D90CA9389A4A8527B"
    },
    "A7A02548BB264FC8A0D0EB2B85008AF5": {
      "id": "A7A02548BB264FC8A0D0EB2B85008AF5",
      "asnIdentifier": null,
      "position": 1007,
      "depth": 2,
      "listId": "6",
      "statementNotation": "8.6",
      "altStatementNotation": null,
      "statementLabel": null,
      "description": "Analyze explicit liberties guaranteed by the US Constitution and explain how these liberties have been used to influence the\nrole and purpose of government.",
      "comments": [],
      "ancestorIds": [
        "D5D9B2C7354D4D3D90CA9389A4A8527B",
        "E35DF215E3134317BFBD60B5CA881084"
      ],
      "parentId": "D5D9B2C7354D4D3D90CA9389A4A8527B"
    },
    "D37DB0ED2F44489E9AD9FC6EFBD3987D": {
      "id": "D37DB0ED2F44489E9AD9FC6EFBD3987D",
      "asnIdentifier": null,
      "position": 1006,
      "depth": 2,
      "listId": "5",
      "statementNotation": "8.5",
      "altStatementNotation": null,
      "statementLabel": null,
      "description": "Evaluate how the role of the US federal government has expanded and contracted historically.",
      "comments": [],
      "ancestorIds": [
        "D5D9B2C7354D4D3D90CA9389A4A8527B",
        "E35DF215E3134317BFBD60B5CA881084"
      ],
      "parentId": "D5D9B2C7354D4D3D90CA9389A4A8527B"
    },
    "B062A8FE4C10428E9394333B447E30CA": {
      "id": "B062A8FE4C10428E9394333B447E30CA",
      "asnIdentifier": null,
      "position": 1005,
      "depth": 2,
      "listId": "4",
      "statementNotation": "8.4",
      "altStatementNotation": null,
      "statementLabel": null,
      "description": "Analyze the historical and philosophical influences on the creation of the American government system, including the role of\nrace, gender, religion, and socioeconomic status.",
      "comments": [],
      "ancestorIds": [
        "D5D9B2C7354D4D3D90CA9389A4A8527B",
        "E35DF215E3134317BFBD60B5CA881084"
      ],
      "parentId": "D5D9B2C7354D4D3D90CA9389A4A8527B"
    },
    "2BEA4B5D17F24356B79FBAD00E8AA380": {
      "id": "2BEA4B5D17F24356B79FBAD00E8AA380",
      "asnIdentifier": null,
      "position": 1004,
      "depth": 2,
      "listId": "3",
      "statementNotation": "8.3",
      "altStatementNotation": null,
      "statementLabel": null,
      "description": "Evaluate major tensions within United States’ constitutional democracy, including majority rule and individual rights, liberty\nand security, civil disobedience and the rule of law, local versus federal control, and the size and scope of the federal government.",
      "comments": [],
      "ancestorIds": [
        "D5D9B2C7354D4D3D90CA9389A4A8527B",
        "E35DF215E3134317BFBD60B5CA881084"
      ],
      "parentId": "D5D9B2C7354D4D3D90CA9389A4A8527B"
    },
    "86E45B205F574F9D918F92558BFC2CE4": {
      "id": "86E45B205F574F9D918F92558BFC2CE4",
      "asnIdentifier": null,
      "position": 1003,
      "depth": 2,
      "listId": "2",
      "statementNotation": "8.2",
      "altStatementNotation": null,
      "statementLabel": null,
      "description": "Use excerpts from documents that shape constitutional democracy in the United States, such as the Declaration of\nIndependence, the Preamble to the Constitution, and the Federalist Papers, to analyze principles about the role of the\ngovernment.",
      "comments": [],
      "ancestorIds": [
        "D5D9B2C7354D4D3D90CA9389A4A8527B",
        "E35DF215E3134317BFBD60B5CA881084"
      ],
      "parentId": "D5D9B2C7354D4D3D90CA9389A4A8527B"
    },
    "93255F3DECE8441D96CC421EF3DC38C0": {
      "id": "93255F3DECE8441D96CC421EF3DC38C0",
      "asnIdentifier": null,
      "position": 1002,
      "depth": 2,
      "listId": "1",
      "statementNotation": "8.1",
      "altStatementNotation": null,
      "statementLabel": null,
      "description": "Evaluate and compare competing ideas for the purpose of government and the role of the people across three different\ncountries or Indigenous Nations. ",
      "comments": [],
      "ancestorIds": [
        "D5D9B2C7354D4D3D90CA9389A4A8527B",
        "E35DF215E3134317BFBD60B5CA881084"
      ],
      "parentId": "D5D9B2C7354D4D3D90CA9389A4A8527B"
    },
    "D5D9B2C7354D4D3D90CA9389A4A8527B": {
      "id": "D5D9B2C7354D4D3D90CA9389A4A8527B",
      "asnIdentifier": null,
      "position": 1001,
      "depth": 1,
      "listId": "",
      "statementNotation": "",
      "altStatementNotation": null,
      "statementLabel": null,
      "description": "This driving concept helps students understand the different global and historical philosophies that inform the role of\ngovernment in society. Students should compare the expectations citizens around the world have regarding the role of\ngovernment to the ways in which residents of the United States view the role of government. Students should also evaluate the\nrole of local government in providing goods or services to residents of the District. Throughout this driving concept, students\nshould evaluate a specific public policy case, and create a proposal about the appropriate level of government intervention in the\npolicy case they are studying.",
      "comments": [],
      "ancestorIds": [
        "E35DF215E3134317BFBD60B5CA881084"
      ],
      "parentId": "E35DF215E3134317BFBD60B5CA881084"
    },
    "E35DF215E3134317BFBD60B5CA881084": {
      "id": "E35DF215E3134317BFBD60B5CA881084",
      "asnIdentifier": null,
      "position": 1000,
      "depth": 0,
      "listId": "1",
      "statementNotation": "",
      "altStatementNotation": null,
      "statementLabel": null,
      "description": "Driving Concept 1: What is the Role of Government in Society?",
      "comments": [],
      "ancestorIds": [],
      "parentId": null
    }
  }
}