{
  "id": "FFF8E9B8B8884EDE9A18189B0A2E7C1C",
  "title": "Business and Marketing Technology: Arkansas Tourism Industry",
  "subject": "CTE (2020-)",
  "normalizedSubject": null,
  "educationLevels": [
    "09",
    "10",
    "11",
    "12"
  ],
  "cspStatus": {},
  "license": {
    "title": "CC BY 4.0 US",
    "URL": "http://creativecommons.org/licenses/by/4.0/us/",
    "rightsHolder": "Common Curriculum, Inc."
  },
  "document": {
    "title": "Arkansas Tourism Industry",
    "sourceURL": "https://drive.google.com/drive/folders/10127Ls0pbNxZApUZXB0Lgt57j9OeURGa"
  },
  "jurisdiction": {
    "id": "2E9F2A0F3440479492D152F02F081AF1",
    "title": "Arkansas"
  },
  "standards": {
    "57E3073A789D4BB1BBCE668AF70ABDBF": {
      "id": "57E3073A789D4BB1BBCE668AF70ABDBF",
      "asnIdentifier": null,
      "position": 1044,
      "depth": 1,
      "listId": "7",
      "statementNotation": "4.3.7",
      "altStatementNotation": null,
      "statementLabel": null,
      "description": "Participate in quarterly work skills\nevaluations. (Evaluations should be similar to\nemployee performance reviews used in the\nworkplace.)",
      "comments": [],
      "ancestorIds": [
        "0A0A3D6899BA40288DE303819AEBFBD3"
      ],
      "parentId": "0A0A3D6899BA40288DE303819AEBFBD3"
    },
    "C9C8C8B3F11441FC879AE415355B65FC": {
      "id": "C9C8C8B3F11441FC879AE415355B65FC",
      "asnIdentifier": null,
      "position": 1043,
      "depth": 1,
      "listId": "4",
      "statementNotation": "4.3.4",
      "altStatementNotation": null,
      "statementLabel": null,
      "description": "Demonstrate good health, hygiene, nutrition,\nand physical fitness habits and discuss how these\ncan help you to be a better employee and have\nimproved quality of life.",
      "comments": [],
      "ancestorIds": [
        "0A0A3D6899BA40288DE303819AEBFBD3"
      ],
      "parentId": "0A0A3D6899BA40288DE303819AEBFBD3"
    },
    "674972F71B8A44AC864EB620645E0A30": {
      "id": "674972F71B8A44AC864EB620645E0A30",
      "asnIdentifier": null,
      "position": 1042,
      "depth": 1,
      "listId": "1",
      "statementNotation": "4.3.1",
      "altStatementNotation": null,
      "statementLabel": null,
      "description": "Demonstrate personal qualities related to\nemployability: promptness, interpersonal skills,\ndependability, initiative, honesty, integrity,\npatience, asking questions, responsibility, respect\nfor diversity, and communication skills.",
      "comments": [],
      "ancestorIds": [
        "0A0A3D6899BA40288DE303819AEBFBD3"
      ],
      "parentId": "0A0A3D6899BA40288DE303819AEBFBD3"
    },
    "0A0A3D6899BA40288DE303819AEBFBD3": {
      "id": "0A0A3D6899BA40288DE303819AEBFBD3",
      "asnIdentifier": null,
      "position": 1041,
      "depth": 0,
      "listId": "4.3",
      "statementNotation": "4.3",
      "altStatementNotation": null,
      "statementLabel": null,
      "description": "Understand and demonstrate job readiness concepts and skills.",
      "comments": [],
      "ancestorIds": [],
      "parentId": null
    },
    "8F077D84C2BA4AB890A818E5F8F0E749": {
      "id": "8F077D84C2BA4AB890A818E5F8F0E749",
      "asnIdentifier": null,
      "position": 1040,
      "depth": 1,
      "listId": "1",
      "statementNotation": "4.1.1",
      "altStatementNotation": null,
      "statementLabel": null,
      "description": "Determine the education required for careers\nin hospitality and tourism and the importance of\nlife-long learning.",
      "comments": [],
      "ancestorIds": [
        "8B77FC7DBF5B457EB1C22CEEB4B37DB4"
      ],
      "parentId": "8B77FC7DBF5B457EB1C22CEEB4B37DB4"
    },
    "8B77FC7DBF5B457EB1C22CEEB4B37DB4": {
      "id": "8B77FC7DBF5B457EB1C22CEEB4B37DB4",
      "asnIdentifier": null,
      "position": 1039,
      "depth": 0,
      "listId": "4.1",
      "statementNotation": "4.1",
      "altStatementNotation": null,
      "statementLabel": null,
      "description": "Understand and demonstrate understanding of educational requirements for career development and advancement.",
      "comments": [],
      "ancestorIds": [],
      "parentId": null
    },
    "45D20D7C007A457BA65B37CF72370C64": {
      "id": "45D20D7C007A457BA65B37CF72370C64",
      "asnIdentifier": null,
      "position": 1037,
      "depth": 1,
      "listId": "5",
      "statementNotation": "3.3.5",
      "altStatementNotation": null,
      "statementLabel": null,
      "description": "Research the local market and generate\nideas about opportunities for new hospitality and\ntourism businesses in the local area. Identify\nunmet wants or needs in the local market and\ndevise a plan to meet those wants and needs.",
      "comments": [],
      "ancestorIds": [
        "201BB9B51511402CAAC8F17D5B05B189"
      ],
      "parentId": "201BB9B51511402CAAC8F17D5B05B189"
    },
    "F041D519B141497C95BEAA2D938F12BE": {
      "id": "F041D519B141497C95BEAA2D938F12BE",
      "asnIdentifier": null,
      "position": 1036,
      "depth": 1,
      "listId": "3",
      "statementNotation": "3.3.3",
      "altStatementNotation": null,
      "statementLabel": null,
      "description": "Determine how advertising and promotion\ntaxes are important to the hospitality and tourism\nindustries.",
      "comments": [],
      "ancestorIds": [
        "201BB9B51511402CAAC8F17D5B05B189"
      ],
      "parentId": "201BB9B51511402CAAC8F17D5B05B189"
    },
    "F4F9ECBB49E94C33AC751A952EF92B73": {
      "id": "F4F9ECBB49E94C33AC751A952EF92B73",
      "asnIdentifier": null,
      "position": 1035,
      "depth": 1,
      "listId": "2",
      "statementNotation": "3.3.2",
      "altStatementNotation": null,
      "statementLabel": null,
      "description": "Identify Visitors and Convention Bureaus,\nand Destination Marketing Organizations (DMOs)\nand determine the role they play in tourism.",
      "comments": [],
      "ancestorIds": [
        "201BB9B51511402CAAC8F17D5B05B189"
      ],
      "parentId": "201BB9B51511402CAAC8F17D5B05B189"
    },
    "201BB9B51511402CAAC8F17D5B05B189": {
      "id": "201BB9B51511402CAAC8F17D5B05B189",
      "asnIdentifier": null,
      "position": 1034,
      "depth": 0,
      "listId": "3.3",
      "statementNotation": "3.3",
      "altStatementNotation": null,
      "statementLabel": null,
      "description": "Understand and explain basic marketing concepts important in hospitality and tourism businesses.\nEssential Learning Targets Applications Resour",
      "comments": [],
      "ancestorIds": [],
      "parentId": null
    },
    "821DBE4C525143718EA43F638B15DD4E": {
      "id": "821DBE4C525143718EA43F638B15DD4E",
      "asnIdentifier": null,
      "position": 1033,
      "depth": 1,
      "listId": "3",
      "statementNotation": "3.2.3",
      "altStatementNotation": null,
      "statementLabel": null,
      "description": "Analyze the impact of changing economic\nconditions that affect Arkansas travel and tourism. ",
      "comments": [],
      "ancestorIds": [
        "19044553928E4BDEB9F1EB0664A9AF12"
      ],
      "parentId": "19044553928E4BDEB9F1EB0664A9AF12"
    },
    "6D1926D735684E4C9A271B03E92CB505": {
      "id": "6D1926D735684E4C9A271B03E92CB505",
      "asnIdentifier": null,
      "position": 1032,
      "depth": 1,
      "listId": "2",
      "statementNotation": "3.2.2",
      "altStatementNotation": null,
      "statementLabel": null,
      "description": "Determine and analyze the liabilities and risk\nof business ownership.",
      "comments": [],
      "ancestorIds": [
        "19044553928E4BDEB9F1EB0664A9AF12"
      ],
      "parentId": "19044553928E4BDEB9F1EB0664A9AF12"
    },
    "19044553928E4BDEB9F1EB0664A9AF12": {
      "id": "19044553928E4BDEB9F1EB0664A9AF12",
      "asnIdentifier": null,
      "position": 1031,
      "depth": 0,
      "listId": "3.2",
      "statementNotation": "3.2",
      "altStatementNotation": null,
      "statementLabel": null,
      "description": "Determine and discuss economic and legal factors affecting Arkansas businesses.",
      "comments": [],
      "ancestorIds": [],
      "parentId": null
    },
    "A78A5B0E9B5F449DA4D9A685D46A982C": {
      "id": "A78A5B0E9B5F449DA4D9A685D46A982C",
      "asnIdentifier": null,
      "position": 1030,
      "depth": 1,
      "listId": "3",
      "statementNotation": "3.1.3",
      "altStatementNotation": null,
      "statementLabel": null,
      "description": "Compare and contrast the characteristics of\nsuccessful and unsuccessful entrepreneurs.",
      "comments": [],
      "ancestorIds": [
        "DE9F01E7B8E74ABF83B839812DE6FB56"
      ],
      "parentId": "DE9F01E7B8E74ABF83B839812DE6FB56"
    },
    "65E4909E3F0343FC9EFBD9BE1D29E7D6": {
      "id": "65E4909E3F0343FC9EFBD9BE1D29E7D6",
      "asnIdentifier": null,
      "position": 1029,
      "depth": 1,
      "listId": "2",
      "statementNotation": "3.1.2",
      "altStatementNotation": null,
      "statementLabel": null,
      "description": "Identify and examine the various professional\norganizations associated with Arkansas\nbusinesses.",
      "comments": [],
      "ancestorIds": [
        "DE9F01E7B8E74ABF83B839812DE6FB56"
      ],
      "parentId": "DE9F01E7B8E74ABF83B839812DE6FB56"
    },
    "3D6F86BF5C494A269606319F0FFC438F": {
      "id": "3D6F86BF5C494A269606319F0FFC438F",
      "asnIdentifier": null,
      "position": 1028,
      "depth": 1,
      "listId": "1",
      "statementNotation": "3.1.1",
      "altStatementNotation": null,
      "statementLabel": null,
      "description": "Identify and categorize various businesses\nthat originated in Arkansas.",
      "comments": [],
      "ancestorIds": [
        "DE9F01E7B8E74ABF83B839812DE6FB56"
      ],
      "parentId": "DE9F01E7B8E74ABF83B839812DE6FB56"
    },
    "DE9F01E7B8E74ABF83B839812DE6FB56": {
      "id": "DE9F01E7B8E74ABF83B839812DE6FB56",
      "asnIdentifier": null,
      "position": 1027,
      "depth": 0,
      "listId": "3.1",
      "statementNotation": "3.1",
      "altStatementNotation": null,
      "statementLabel": null,
      "description": "Examine and deliberate on businesses that originated in Arkansas as well as professional organizations associated with Arkansas businesses.",
      "comments": [],
      "ancestorIds": [],
      "parentId": null
    },
    "D0CB2785D2B4405BBAE32F188B188BE5": {
      "id": "D0CB2785D2B4405BBAE32F188B188BE5",
      "asnIdentifier": null,
      "position": 1025,
      "depth": 1,
      "listId": "5",
      "statementNotation": "2.3.5",
      "altStatementNotation": null,
      "statementLabel": null,
      "description": "Determine the careers available in the\ntransportation industry.",
      "comments": [],
      "ancestorIds": [
        "AFA6B07BBB9A4FE18BCA9018B198D018"
      ],
      "parentId": "AFA6B07BBB9A4FE18BCA9018B198D018"
    },
    "90A26CFA6ED649B6926CBA78EF95D560": {
      "id": "90A26CFA6ED649B6926CBA78EF95D560",
      "asnIdentifier": null,
      "position": 1024,
      "depth": 1,
      "listId": "3",
      "statementNotation": "2.3.3",
      "altStatementNotation": null,
      "statementLabel": null,
      "description": "Understand the economic impact of the\ntransportation industry on the Arkansas economy.",
      "comments": [],
      "ancestorIds": [
        "AFA6B07BBB9A4FE18BCA9018B198D018"
      ],
      "parentId": "AFA6B07BBB9A4FE18BCA9018B198D018"
    },
    "EA61015849F9400C868BC891BD5DCEED": {
      "id": "EA61015849F9400C868BC891BD5DCEED",
      "asnIdentifier": null,
      "position": 1023,
      "depth": 1,
      "listId": "1",
      "statementNotation": "2.3.1",
      "altStatementNotation": null,
      "statementLabel": null,
      "description": "Analyze the Arkansas infrastructure for rail,\nair, land and water, including the challenges,\nstrengths and deficiencies of each.",
      "comments": [],
      "ancestorIds": [
        "AFA6B07BBB9A4FE18BCA9018B198D018"
      ],
      "parentId": "AFA6B07BBB9A4FE18BCA9018B198D018"
    },
    "AFA6B07BBB9A4FE18BCA9018B198D018": {
      "id": "AFA6B07BBB9A4FE18BCA9018B198D018",
      "asnIdentifier": null,
      "position": 1022,
      "depth": 0,
      "listId": "2.3",
      "statementNotation": "2.3",
      "altStatementNotation": null,
      "statementLabel": null,
      "description": "Analyze the transportation industry and the impact of the transportation infrastructure on the travel and tourism industry. ",
      "comments": [],
      "ancestorIds": [],
      "parentId": null
    },
    "AB887DFFDCA14079B4B9B13F742B6FF3": {
      "id": "AB887DFFDCA14079B4B9B13F742B6FF3",
      "asnIdentifier": null,
      "position": 1021,
      "depth": 1,
      "listId": "8",
      "statementNotation": "2.2.8",
      "altStatementNotation": null,
      "statementLabel": null,
      "description": "Research, examine and explore Agri-tourism\nand Farm-to-Table",
      "comments": [],
      "ancestorIds": [
        "A0A867BC43724EFB9BCB04460F689A5A"
      ],
      "parentId": "A0A867BC43724EFB9BCB04460F689A5A"
    },
    "F99E1F0A001C43F1A03877D4371A704E": {
      "id": "F99E1F0A001C43F1A03877D4371A704E",
      "asnIdentifier": null,
      "position": 1020,
      "depth": 1,
      "listId": "6",
      "statementNotation": "2.2.6",
      "altStatementNotation": null,
      "statementLabel": null,
      "description": "Determine the careers available in the\ntourism industry",
      "comments": [],
      "ancestorIds": [
        "A0A867BC43724EFB9BCB04460F689A5A"
      ],
      "parentId": "A0A867BC43724EFB9BCB04460F689A5A"
    },
    "28FD458E6B924703BF04565AF86B219A": {
      "id": "28FD458E6B924703BF04565AF86B219A",
      "asnIdentifier": null,
      "position": 1019,
      "depth": 1,
      "listId": "5",
      "statementNotation": "2.2.5",
      "altStatementNotation": null,
      "statementLabel": null,
      "description": "Discover the different festivals in the state\nand describe the featured foods, crafts, and the\ncities where the festivals are located.",
      "comments": [],
      "ancestorIds": [
        "A0A867BC43724EFB9BCB04460F689A5A"
      ],
      "parentId": "A0A867BC43724EFB9BCB04460F689A5A"
    },
    "1C69B22A9B99459588727F1B68DEFFA4": {
      "id": "1C69B22A9B99459588727F1B68DEFFA4",
      "asnIdentifier": null,
      "position": 1018,
      "depth": 1,
      "listId": "3",
      "statementNotation": "2.2.3",
      "altStatementNotation": null,
      "statementLabel": null,
      "description": "Explain the tourism industry as it relates to\nsports, including any professional sports facilities,\ncollege athletic programs, marathons, hunting\nsports, hall of fame, etc.",
      "comments": [],
      "ancestorIds": [
        "A0A867BC43724EFB9BCB04460F689A5A"
      ],
      "parentId": "A0A867BC43724EFB9BCB04460F689A5A"
    },
    "FEF51ECA0D634C7880B6293EAFDAC01D": {
      "id": "FEF51ECA0D634C7880B6293EAFDAC01D",
      "asnIdentifier": null,
      "position": 1017,
      "depth": 1,
      "listId": "1",
      "statementNotation": "2.2.1",
      "altStatementNotation": null,
      "statementLabel": null,
      "description": "Locate and examine the various types of\nparks in Arkansas, i.e. city, state, and national",
      "comments": [],
      "ancestorIds": [
        "A0A867BC43724EFB9BCB04460F689A5A"
      ],
      "parentId": "A0A867BC43724EFB9BCB04460F689A5A"
    },
    "A0A867BC43724EFB9BCB04460F689A5A": {
      "id": "A0A867BC43724EFB9BCB04460F689A5A",
      "asnIdentifier": null,
      "position": 1016,
      "depth": 0,
      "listId": "2.2",
      "statementNotation": "2.2",
      "altStatementNotation": null,
      "statementLabel": null,
      "description": "Evaluate and discuss the tourism in Arkansas and its economic relevance to Arkansas communities, regions, and the\nstate as a whole.",
      "comments": [],
      "ancestorIds": [],
      "parentId": null
    },
    "9D1DC177110C4C6ABDBD2E360D04016D": {
      "id": "9D1DC177110C4C6ABDBD2E360D04016D",
      "asnIdentifier": null,
      "position": 1015,
      "depth": 1,
      "listId": "8",
      "statementNotation": "2.1.8",
      "altStatementNotation": null,
      "statementLabel": null,
      "description": "Research, identify and explain trends in\nlodging industry; Airbnb, VRBO, agritourism, etc.",
      "comments": [],
      "ancestorIds": [
        "6B41D8D38E6E4BCF88A5C641762407AA"
      ],
      "parentId": "6B41D8D38E6E4BCF88A5C641762407AA"
    },
    "C2D631E527F54D879BC8165DC7FC334E": {
      "id": "C2D631E527F54D879BC8165DC7FC334E",
      "asnIdentifier": null,
      "position": 1014,
      "depth": 1,
      "listId": "6",
      "statementNotation": "2.1.6",
      "altStatementNotation": null,
      "statementLabel": null,
      "description": "Determine and analyze the economic impact\nof the lodging industry in Arkansas ",
      "comments": [],
      "ancestorIds": [
        "6B41D8D38E6E4BCF88A5C641762407AA"
      ],
      "parentId": "6B41D8D38E6E4BCF88A5C641762407AA"
    },
    "845F95797A894FA0BF58A3BE73FEDA40": {
      "id": "845F95797A894FA0BF58A3BE73FEDA40",
      "asnIdentifier": null,
      "position": 1013,
      "depth": 1,
      "listId": "5",
      "statementNotation": "2.1.5",
      "altStatementNotation": null,
      "statementLabel": null,
      "description": "Identify the types of lodging available in\nArkansas, including hotel, motel, bed and\nbreakfast, resort, CRP7 camping, and time shares.\nAnalyze how each option meets consumer\nswants/needs.",
      "comments": [],
      "ancestorIds": [
        "6B41D8D38E6E4BCF88A5C641762407AA"
      ],
      "parentId": "6B41D8D38E6E4BCF88A5C641762407AA"
    },
    "C2367CC113CC42B691FF2243D1AD96F7": {
      "id": "C2367CC113CC42B691FF2243D1AD96F7",
      "asnIdentifier": null,
      "position": 1012,
      "depth": 1,
      "listId": "3",
      "statementNotation": "2.1.3",
      "altStatementNotation": null,
      "statementLabel": null,
      "description": "Research the various types of cuisine,\nservice styles, restaurants and their price ranges.",
      "comments": [],
      "ancestorIds": [
        "6B41D8D38E6E4BCF88A5C641762407AA"
      ],
      "parentId": "6B41D8D38E6E4BCF88A5C641762407AA"
    },
    "0392954F7376432BBF1A678A1A84828B": {
      "id": "0392954F7376432BBF1A678A1A84828B",
      "asnIdentifier": null,
      "position": 1011,
      "depth": 1,
      "listId": "1",
      "statementNotation": "2.1.1",
      "altStatementNotation": null,
      "statementLabel": null,
      "description": "Explain the food and agricultural industry in\nArkansas and the impact the industry has on local,\nstate, and the national economy.",
      "comments": [],
      "ancestorIds": [
        "6B41D8D38E6E4BCF88A5C641762407AA"
      ],
      "parentId": "6B41D8D38E6E4BCF88A5C641762407AA"
    },
    "6B41D8D38E6E4BCF88A5C641762407AA": {
      "id": "6B41D8D38E6E4BCF88A5C641762407AA",
      "asnIdentifier": null,
      "position": 1010,
      "depth": 0,
      "listId": "2.1",
      "statementNotation": "2.1",
      "altStatementNotation": null,
      "statementLabel": null,
      "description": "Evaluate and discuss the hospitality industry in Arkansas and its economic relevance to Arkansas communities, regions,\nand the state as a whole.",
      "comments": [],
      "ancestorIds": [],
      "parentId": null
    },
    "41A54067986E4568AD696C6709F2FC32": {
      "id": "41A54067986E4568AD696C6709F2FC32",
      "asnIdentifier": null,
      "position": 1008,
      "depth": 1,
      "listId": "3",
      "statementNotation": "1.2.3",
      "altStatementNotation": null,
      "statementLabel": null,
      "description": "Identify and describe the major tourist\nattractions in each region and discuss how these\nfeatures relate to consumer wants/needs. ",
      "comments": [],
      "ancestorIds": [
        "C5F75BE8A49440C98267EC89D0311763"
      ],
      "parentId": "C5F75BE8A49440C98267EC89D0311763"
    },
    "D041900E62644131A867D95363C4A0AE": {
      "id": "D041900E62644131A867D95363C4A0AE",
      "asnIdentifier": null,
      "position": 1007,
      "depth": 1,
      "listId": "1",
      "statementNotation": "1.2.1",
      "altStatementNotation": null,
      "statementLabel": null,
      "description": "Locate and list the city, state and national\nparks in each region.",
      "comments": [],
      "ancestorIds": [
        "C5F75BE8A49440C98267EC89D0311763"
      ],
      "parentId": "C5F75BE8A49440C98267EC89D0311763"
    },
    "C5F75BE8A49440C98267EC89D0311763": {
      "id": "C5F75BE8A49440C98267EC89D0311763",
      "asnIdentifier": null,
      "position": 1006,
      "depth": 0,
      "listId": "1.2",
      "statementNotation": "1.2",
      "altStatementNotation": null,
      "statementLabel": null,
      "description": "Describe the parks and tourist attractions in each region.",
      "comments": [],
      "ancestorIds": [],
      "parentId": null
    },
    "BCD815925D78455B9C9A43390BC81BDA": {
      "id": "BCD815925D78455B9C9A43390BC81BDA",
      "asnIdentifier": null,
      "position": 1005,
      "depth": 1,
      "listId": "4",
      "statementNotation": "1.1.4",
      "altStatementNotation": null,
      "statementLabel": null,
      "description": "Identify and label the counties in each region.",
      "comments": [],
      "ancestorIds": [
        "B0F692CBE6A14C89828CA6503E93542D"
      ],
      "parentId": "B0F692CBE6A14C89828CA6503E93542D"
    },
    "8B2FA8C0D6F946B1A045CF0EA3B8AC4C": {
      "id": "8B2FA8C0D6F946B1A045CF0EA3B8AC4C",
      "asnIdentifier": null,
      "position": 1004,
      "depth": 1,
      "listId": "3",
      "statementNotation": "1.1.3",
      "altStatementNotation": null,
      "statementLabel": null,
      "description": "Research and explain the economic\nconditions of each region. ",
      "comments": [],
      "ancestorIds": [
        "B0F692CBE6A14C89828CA6503E93542D"
      ],
      "parentId": "B0F692CBE6A14C89828CA6503E93542D"
    },
    "B91544F5AD19427192327726EF423EA4": {
      "id": "B91544F5AD19427192327726EF423EA4",
      "asnIdentifier": null,
      "position": 1003,
      "depth": 1,
      "listId": "2",
      "statementNotation": "1.1.2",
      "altStatementNotation": null,
      "statementLabel": null,
      "description": "Examine the various demographics in each\ngeographic region and how this affects consumer\nbehaviors in each region.",
      "comments": [],
      "ancestorIds": [
        "B0F692CBE6A14C89828CA6503E93542D"
      ],
      "parentId": "B0F692CBE6A14C89828CA6503E93542D"
    },
    "4C701439793F4AC4BC2F024C2815E552": {
      "id": "4C701439793F4AC4BC2F024C2815E552",
      "asnIdentifier": null,
      "position": 1002,
      "depth": 1,
      "listId": "1",
      "statementNotation": "1.1.1",
      "altStatementNotation": null,
      "statementLabel": null,
      "description": "Identify the different geographic regions.",
      "comments": [],
      "ancestorIds": [
        "B0F692CBE6A14C89828CA6503E93542D"
      ],
      "parentId": "B0F692CBE6A14C89828CA6503E93542D"
    },
    "B0F692CBE6A14C89828CA6503E93542D": {
      "id": "B0F692CBE6A14C89828CA6503E93542D",
      "asnIdentifier": null,
      "position": 1001,
      "depth": 0,
      "listId": "1.1",
      "statementNotation": "1.1",
      "altStatementNotation": null,
      "statementLabel": null,
      "description": " Identify, analyze, and explain the various geographic reasons in the State of Arkansas.",
      "comments": [],
      "ancestorIds": [],
      "parentId": null
    }
  }
}